oxl_opnsense_client/__init__.py
oxl_opnsense_client/basic/__init__.py
oxl_opnsense_client/basic/ansible.py
oxl_opnsense_client/basic/ansible_pytest.py
oxl_opnsense_client/basic/client.py
oxl_opnsense_client/basic/client_pytest.py
oxl_opnsense_client/basic/exceptions.py
oxl_opnsense_client/basic/exceptions_pytest.py
oxl_opnsense_client/basic/handler.py
oxl_opnsense_client/basic/handler_pytest.py
oxl_opnsense_client/plugins/__init__.py
oxl_opnsense_client/plugins/module_utils/__init__.py
oxl_opnsense_client/plugins/module_utils/base/__init__.py
oxl_opnsense_client/plugins/module_utils/base/api.py
oxl_opnsense_client/plugins/module_utils/base/api_base_pytest.py
oxl_opnsense_client/plugins/module_utils/base/base.py
oxl_opnsense_client/plugins/module_utils/base/base_pytest.py
oxl_opnsense_client/plugins/module_utils/base/cls.py
oxl_opnsense_client/plugins/module_utils/base/cls_base_pytest.py
oxl_opnsense_client/plugins/module_utils/base/handler.py
oxl_opnsense_client/plugins/module_utils/base/handler_base_pytest.py
oxl_opnsense_client/plugins/module_utils/base/multi.py
oxl_opnsense_client/plugins/module_utils/base/multi_base_1_mod_args_pytest.py
oxl_opnsense_client/plugins/module_utils/base/multi_base_2_parts_pytest.py
oxl_opnsense_client/plugins/module_utils/base/multi_base_3_full_pytest.py
oxl_opnsense_client/plugins/module_utils/base/wrapper.py
oxl_opnsense_client/plugins/module_utils/base/wrapper_base_pytest.py
oxl_opnsense_client/plugins/module_utils/defaults/__init__.py
oxl_opnsense_client/plugins/module_utils/defaults/alias.py
oxl_opnsense_client/plugins/module_utils/defaults/alias_defaults_pytest.py
oxl_opnsense_client/plugins/module_utils/defaults/bind.py
oxl_opnsense_client/plugins/module_utils/defaults/ipsec_auth.py
oxl_opnsense_client/plugins/module_utils/defaults/ipsec_auth_defaults_pytest.py
oxl_opnsense_client/plugins/module_utils/defaults/legacy_multi.py
oxl_opnsense_client/plugins/module_utils/defaults/legacy_multi_defaults_pytest.py
oxl_opnsense_client-25.7.7.dist-info/licenses/LICENSE
oxl_opnsense_client-25.7.7.dist-info/METADATA
oxl_opnsense_client-25.7.7.dist-info/WHEEL
oxl_opnsense_client-25.7.7.dist-info/top_level.txt
oxl_opnsense_client-25.7.7.dist-info/RECORD
