Metadata-Version: 2.4
Name: oxl-opnsense-client
Version: 25.7.7
Summary: OXL OPNsense API Client
Author-email: Rath Pascal <contact@oxl.at>
Project-URL: Homepage, https://www.OXL.at
Project-URL: Documentation, https://python-opnsense.oxl.app
Project-URL: Repository, https://github.com/O-X-L/opnsense-api-client.git
Project-URL: Issues, https://github.com/O-X-L/opnsense-api-client/issues
Keywords: api,client,opnsense,firewall,network,network-as-code,nac,infrastructure-as-code,iac
Classifier: Programming Language :: Python :: 3
Classifier: License :: OSI Approved :: GNU General Public License v3 (GPLv3)
Requires-Python: >=3.10
License-File: LICENSE
Requires-Dist: httpx
Requires-Dist: ansible-core==2.19.*
Dynamic: license-file
